rescape_python_helpers/__init__.py
rescape_python_helpers/functional/__init__.py
rescape_python_helpers/functional/memoize.py
rescape_python_helpers/functional/ramda.py
rescape_python_helpers/functional/ramda_test.py
rescape_python_helpers/pyramda/__init__.py
rescape_python_helpers/pyramda/getattr.py
rescape_python_helpers/pyramda/getattr_test.py
rescape_python_helpers/pyramda/isinstance.py
rescape_python_helpers/pyramda/isinstance_test.py
rescape_python_helpers/pyramda/dictionary/__init__.py
rescape_python_helpers/pyramda/dictionary/getitem.py
rescape_python_helpers/pyramda/dictionary/getitem_test.py
rescape_python_helpers/pyramda/dictionary/item_path.py
rescape_python_helpers/pyramda/dictionary/item_path_test.py
rescape_python_helpers/pyramda/dictionary/keys.py
rescape_python_helpers/pyramda/dictionary/keys_test.py
rescape_python_helpers/pyramda/dictionary/map_dict.py
rescape_python_helpers/pyramda/dictionary/map_dict_test.py
rescape_python_helpers/pyramda/dictionary/pick.py
rescape_python_helpers/pyramda/dictionary/pick_test.py
rescape_python_helpers/pyramda/dictionary/values.py
rescape_python_helpers/pyramda/dictionary/values_test.py
rescape_python_helpers/pyramda/function/__init__.py
rescape_python_helpers/pyramda/function/always.py
rescape_python_helpers/pyramda/function/always_test.py
rescape_python_helpers/pyramda/function/apply.py
rescape_python_helpers/pyramda/function/apply_test.py
rescape_python_helpers/pyramda/function/compose.py
rescape_python_helpers/pyramda/function/compose_test.py
rescape_python_helpers/pyramda/function/curry.py
rescape_python_helpers/pyramda/function/curry_test.py
rescape_python_helpers/pyramda/function/flip.py
rescape_python_helpers/pyramda/function/flip_test.py
rescape_python_helpers/pyramda/function/identity.py
rescape_python_helpers/pyramda/function/identity_test.py
rescape_python_helpers/pyramda/function/pipe.py
rescape_python_helpers/pyramda/function/pipe_test.py
rescape_python_helpers/pyramda/function/tap.py
rescape_python_helpers-0.0.66.dist-info/LICENSE
rescape_python_helpers-0.0.66.dist-info/METADATA
rescape_python_helpers-0.0.66.dist-info/WHEEL
rescape_python_helpers-0.0.66.dist-info/top_level.txt
rescape_python_helpers-0.0.66.dist-info/RECORD
