Metadata-Version: 2.1
Name: rescape-python-helpers
Version: 0.0.66
Summary: Functional and geospatial helpers for Rescape projects. Pyramda library by from https://github.com/jackfirth/pyramda incorporated in after it stopped working with new Python relases
Home-page: https://github.com/calocan/rescape-python-helpers
Author: Andy Likuski
Author-email: andy@likuski.org
Classifier: Programming Language :: Python :: 3
Classifier: License :: OSI Approved :: MIT License
Classifier: Operating System :: OS Independent
License-File: LICENSE
Requires-Dist: pyramda
Requires-Dist: inflection
Requires-Dist: deepmerge
